celerymon/__init__.py
celerymon/defaults.py
celerymon/models.py
celerymon/test_cases.py
celerymon/test_settings.py
celerymon/management/__init__.py
celerymon/management/commands/__init__.py
celerymon/management/commands/check_celery_state.py
django_celery_mon-1.0.dist-info/DESCRIPTION.rst
django_celery_mon-1.0.dist-info/METADATA
django_celery_mon-1.0.dist-info/metadata.json
django_celery_mon-1.0.dist-info/RECORD
django_celery_mon-1.0.dist-info/top_level.txt
django_celery_mon-1.0.dist-info/WHEEL
